carbatpy/__init__.py
carbatpy/cb_config.py
carbatpy/data/2023-12-15-18-20heat_pump
carbatpy/data/2023-12-15-18-20heat_pump.png
carbatpy/data/2023-12-15-18-20orc
carbatpy/data/2023-12-15-18-20orc.png
carbatpy/data/2023-12-20-15-06orc
carbatpy/data/2023-12-20-15-06orc.png
carbatpy/data/2023-12-20-15-07heat_pump
carbatpy/data/2023-12-20-15-07heat_pump.png
carbatpy/data/2024-01-07-18-58heat_pump
carbatpy/data/2024-01-07-18-58heat_pump.png
carbatpy/data/2024-01-07-18-58orc
carbatpy/data/2024-01-07-18-58orc.png
carbatpy/data/2024-01-07-19-03heat_pump
carbatpy/data/2024-01-07-19-03heat_pump.png
carbatpy/data/2024-01-07-19-03orc
carbatpy/data/2024-01-07-19-03orc.png
carbatpy/data/BA106410
carbatpy/data/Capital_Investment_Methods_ba.xlsx
carbatpy/data/cycle.gv
carbatpy/data/cycle.gv.pdf
carbatpy/data/def_hyperparameter.yaml
carbatpy/data/Example_compressor_data.csv
carbatpy/data/hp-input-dict_opt.json
carbatpy/data/hp-input-dict_opt_px.json
carbatpy/data/hp-input-dict_opt_px20250124.json
carbatpy/data/hp-input-dictvariables
carbatpy/data/hp-input-dictvariables-hp-last.json
carbatpy/data/hp-input-dictvariables.json
carbatpy/data/hp-input-dictvariables.yaml
carbatpy/data/hp-input-dictvariables2024-07-27.json
carbatpy/data/hp-input-dictvariables_0.json
carbatpy/data/hp-input-dictvariables_0.yaml
carbatpy/data/hp_structure.xlsx
carbatpy/data/input_hp_orc_unified.json
carbatpy/data/io-cycle-data.yaml
carbatpy/data/io-orc-data.yaml
carbatpy/data/ORC.gv
carbatpy/data/ORC.gv.pdf
carbatpy/data/orc_structure.xlsx
carbatpy/data/~$orc_structure.xlsx
carbatpy/examples/2025-08-06-output.txt
carbatpy/examples/2025-08-06b-output.txt
carbatpy/examples/comp_example_heat_pump.ipynb
carbatpy/examples/comp_example_heat_pump.py
carbatpy/examples/comp_example_heat_pump_old.py
carbatpy/examples/fluid_example.ipynb
carbatpy/examples/fluid_example.py
carbatpy/examples/heat_pump_example.ipynb
carbatpy/examples/heat_pump_example.py
carbatpy/examples/hex_example.py
carbatpy-0.5.4.post1.dist-info/AUTHORS.rst
carbatpy-0.5.4.post1.dist-info/LICENSE
carbatpy-0.5.4.post1.dist-info/METADATA
carbatpy-0.5.4.post1.dist-info/WHEEL
carbatpy-0.5.4.post1.dist-info/RECORD
