Metadata-Version: 2.3
Name: carbatpy
Version: 0.5.4.post1
Summary: Calculate and optimize Carnot Batteries (Thermal energy storage)
Home-page: https://git.uni-due.de/spp-2403/td-ude/carbatpy
License: MIT
Keywords: thermal-energy-storage, heat-exchanger, thermodynmics,heat transfer
Author: Burak Atakan
Author-email: b.atakan@uni-duisburg.de
Requires-Python: >=3.10
Classifier: Development Status :: 3 - Alpha
Classifier: Topic :: Scientific/Engineering
Classifier: License :: OSI Approved :: MIT License
Requires-Dist: SALib (>=1.5.0,<2.0.0)
Requires-Dist: coolprop (>=6.6.0,<7.0.0)
Requires-Dist: ctrefprop (>=0.10.2,<0.11.0)
Requires-Dist: fluids (>=1.2.0,<2.0.0)
Requires-Dist: graphviz (>=0.20.3,<0.21.0)
Requires-Dist: ht (>=1.1.0,<2.0.0)
Requires-Dist: joblib (>=1.4.2,<2.0.0)
Requires-Dist: matplotlib (>=3.9.1,<4.0.0)
Requires-Dist: numpy (>=2.0.0,<3.0.0)
Requires-Dist: openpyxl (>=3.1.5,<4.0.0)
Requires-Dist: pandas (>=2.2.2,<3.0.0)
Requires-Dist: pyyaml (>=6.0.1,<7.0.0)
Requires-Dist: scikit-learn (>=1.5.1,<2.0.0)
Requires-Dist: scipy (>=1.14.0,<2.0.0)
Requires-Dist: seaborn (>=0.13.2,<0.14.0)
Requires-Dist: toml (>=0.10.2,<0.11.0)
Project-URL: Documentation, https://carbatpy-010.readthedocs.io/en/latest/
Project-URL: Repository, https://git.uni-due.de/spp-2403/td-ude/carbatpy
